package_trader/__init__.py
package_trader/collect_dates/__init__.py
package_trader/collect_dates/collect_dates.py
package_trader/forecast/__init__.py
package_trader/forecast/forecast.py
package_trader/main/__init__.py
package_trader/main/main.py
package_trader/model/__init__.py
package_trader/model/model.py
package_trader/process/__init__.py
package_trader/process/process.py
package_trade-0.1.0.dist-info/LICENSE
package_trade-0.1.0.dist-info/METADATA
package_trade-0.1.0.dist-info/WHEEL
package_trade-0.1.0.dist-info/top_level.txt
package_trade-0.1.0.dist-info/RECORD
