Metadata-Version: 2.2
Name: package_trade
Version: 0.1.0
Summary: Trade program
Home-page: https://github.com/DanrleyS/Machine_learn_prever_valor_acoes
Author: Danrley
Author-email: seu_email@example.com
License: MIT
License-File: LICENSE
Requires-Dist: pandas
Requires-Dist: numpy
Requires-Dist: yfinance
Requires-Dist: matplotlib
Requires-Dist: scikit-learn
Dynamic: author
Dynamic: author-email
Dynamic: description
Dynamic: description-content-type
Dynamic: home-page
Dynamic: license
Dynamic: requires-dist
Dynamic: summary
